psense_common/__init__.py
psense_common/analysis/__init__.py
psense_common/analysis/calibration.py
psense_common/analysis/excelwriter.py
psense_common/analysis/response.py
psense_common/kfilter.py
psense_common/psense_aws_itfc.py
psense_common/psense_format.py
psense_common/psense_parser.py
psense_common-0.4.11.dist-info/METADATA
psense_common-0.4.11.dist-info/WHEEL
psense_common-0.4.11.dist-info/RECORD
