Metadata-Version: 2.1
Name: psense-common
Version: 0.4.11
Summary: PercuSense Common Modules
Author: PercuSense
Author-email: info@percusense.com
Requires-Python: >3.9,<3.13
Classifier: Programming Language :: Python :: 3
Classifier: Programming Language :: Python :: 3.10
Classifier: Programming Language :: Python :: 3.11
Classifier: Programming Language :: Python :: 3.12
Requires-Dist: XlsxWriter (>=3.1.9,<4.0.0)
Requires-Dist: boto3 (>=1.28.82,<2.0.0)
Requires-Dist: pandas (>=2.1.2,<3.0.0)
Requires-Dist: scipy (>=1.11.3,<2.0.0)
